Workbook

Sheet Danh muc Test Case
A1: STT | B1: Tầng | C1: Tệp | D1: Nhóm chức năng | E1: Tên test case | F1: Số ca chạy | G1: Ý nghĩa và cách thực thi
A2: 1 | B2: Unit | C2: test_ai_report.py | D2: TestLocThongTinNhayCam | E2: test_che_duoc_thong_tin_nhay_cam | F2: 9 | G2: 【Ý NGHĨA】 Che duoc thong tin nhay cam. (Nhóm: Không được để lọt mật khẩu, khoá API hay đường dẫn cá nhân ra ngoài.) 【DỮ LIỆU CHUẨN BỊ】 • dau_vao: — • khong_duoc_chua: — 【CHẠY LẶP NHIỀU BỘ DỮ LIỆU】 pytest.mark.parametrize('dau_vao,khong_duoc_chua', [('DB_PASSWORD=MatKhauSieuBiMat123', 'MatKhauSieuBiMat123'), ('SERVER=localhost;UID=pcparts_user;PWD=Secret@99;', 'Secret@99'), ("api_key = 'sk-ant-a 【CÁC BƯỚC THỰC THI】 1. ket_qua = redact.loc_van_ban(dau_vao) 【KẾT QUẢ MONG ĐỢI】 ✓ khong_duoc_chua not in ket_qua ✓ redact.NHAN_CHE in ket_qua
A3: 2 | B3: Unit | C3: test_ai_report.py | D3: TestLocThongTinNhayCam | E3: test_giu_nguyen_email_dung_trong_test | F3: 1 | G3: 【Ý NGHĨA】 Email của dữ liệu test không phải thông tin thật, giữ lại cho dễ đọc. (Nhóm: Không được để lọt mật khẩu, khoá API hay đường dẫn cá nhân ra ngoài.) 【KẾT QUẢ MONG ĐỢI】 ✓ "khachhang@test.vn" in redact.loc_van_ban("user = 'khachhang@test.vn'")
A4: 3 | B4: Unit | C4: test_ai_report.py | D4: TestLocThongTinNhayCam | E4: test_khong_con_sot_sau_khi_loc | F4: 1 | G4: 【Ý NGHĨA】 Khong con sot sau khi loc. (Nhóm: Không được để lọt mật khẩu, khoá API hay đường dẫn cá nhân ra ngoài.) 【CÁC BƯỚC THỰC THI】 1. ban_do = ("DB_PASSWORD=abc123 PWD=xyz789 sk-ant-api03-qwertyuiopasdfgh " r"C:\Users\PC\x.py /home/ai/y.py that@gmail.com") 【KẾT QUẢ MONG ĐỢI】 ✓ redact.kiem_tra_con_sot(redact.loc_van_ban(ban_do)) == []
A5: 4 | B5: Unit | C5: test_ai_report.py | D5: TestLocThongTinNhayCam | E5: test_loc_hai_lan_cho_ket_qua_giong_nhau | F5: 1 | G5: 【Ý NGHĨA】 Lọc lại chuỗi đã lọc không được làm hỏng thêm. (Nhóm: Không được để lọt mật khẩu, khoá API hay đường dẫn cá nhân ra ngoài.) 【CÁC BƯỚC THỰC THI】 1. goc = "DB_PASSWORD=bimat và PWD=khac" 2. mot_lan = redact.loc_van_ban(goc) 【KẾT QUẢ MONG ĐỢI】 ✓ redact.loc_van_ban(mot_lan) == mot_lan
A6: 5 | B6: Unit | C6: test_ai_report.py | D6: TestLocThongTinNhayCam | E6: test_loc_duoc_cau_truc_long_nhau | F6: 1 | G6: 【Ý NGHĨA】 Loc duoc cau truc long nhau. (Nhóm: Không được để lọt mật khẩu, khoá API hay đường dẫn cá nhân ra ngoài.) 【CÁC BƯỚC THỰC THI】 1. du_lieu = {"a": ["DB_PASSWORD=bimat"], "b": {"c": "sk-ant-api03-abcdefghijklmnop"}} 2. ket_qua = redact.loc_du_lieu(du_lieu) 【KẾT QUẢ MONG ĐỢI】 ✓ "bimat" not in json.dumps(ket_qua) ✓ "sk-ant" not in json.dumps(ket_qua)
A7: 6 | B7: Unit | C7: test_ai_report.py | D7: TestLocThongTinNhayCam | E7: test_chuoi_rong_khong_gay_loi | F7: 1 | G7: 【Ý NGHĨA】 Chuoi rong khong gay loi. (Nhóm: Không được để lọt mật khẩu, khoá API hay đường dẫn cá nhân ra ngoài.) 【KẾT QUẢ MONG ĐỢI】 ✓ redact.loc_van_ban("") == "" ✓ redact.loc_van_ban(None) == ""
A8: 7 | B8: Unit | C8: test_ai_report.py | D8: TestDocKetQua | E8: test_bao_loi_khi_thieu_tep | F8: 1 | G8: 【Ý NGHĨA】 Bao loi khi thieu tep. 【DỮ LIỆU CHUẨN BỊ】 • tmp_path: thư mục tạm 【KẾT QUẢ MONG ĐỢI】 ✓ Ném ngoại lệ FileNotFoundError ✓ "--json-report" in str(loi.value)
A9: 8 | B9: Unit | C9: test_ai_report.py | D9: TestDocKetQua | E9: test_tom_tat_dung_so_lieu | F9: 1 | G9: 【Ý NGHĨA】 Tom tat dung so lieu. 【DỮ LIỆU CHUẨN BỊ】 • bao_cao_mau: — 【CÁC BƯỚC THỰC THI】 1. tt = collect.tom_tat(collect.doc_bao_cao(bao_cao_mau)) 【KẾT QUẢ MONG ĐỢI】 ✓ (tt["tong"], tt["dat"], tt["hong"]) == (100, 97, 3) ✓ tt["thoi_gian"] == 12.34
A10: 9 | B10: Unit | C10: test_ai_report.py | D10: TestDocKetQua | E10: test_chi_trich_cac_ca_that_bai | F10: 1 | G10: 【Ý NGHĨA】 Chi trich cac ca that bai. 【DỮ LIỆU CHUẨN BỊ】 • bao_cao_mau: — 【CÁC BƯỚC THỰC THI】 1. cac_ca = collect.trich_ca_loi(collect.doc_bao_cao(bao_cao_mau)) 【KẾT QUẢ MONG ĐỢI】 ✓ len(cac_ca) == 3 ✓ all("test_ok" not in c.ten for c in cac_ca)
A11: 10 | B11: Unit | C11: test_ai_report.py | D11: TestDocKetQua | E11: test_nhan_dien_dung_tang | F11: 1 | G11: 【Ý NGHĨA】 Nhan dien dung tang. 【DỮ LIỆU CHUẨN BỊ】 • bao_cao_mau: — 【CÁC BƯỚC THỰC THI】 1. cac_ca = collect.trich_ca_loi(collect.doc_bao_cao(bao_cao_mau)) 【KẾT QUẢ MONG ĐỢI】 ✓ {c.tang for c in cac_ca} == {"unit", "e2e"}
A12: 11 | B12: Unit | C12: test_ai_report.py | D12: TestDocKetQua | E12: test_bo_tien_to_E_cua_pytest | F12: 1 | G12: 【Ý NGHĨA】 Bo tien to E cua pytest. 【DỮ LIỆU CHUẨN BỊ】 • bao_cao_mau: — 【CÁC BƯỚC THỰC THI】 1. cac_ca = collect.trich_ca_loi(collect.doc_bao_cao(bao_cao_mau)) 【KẾT QUẢ MONG ĐỢI】 ✓ all(not c.thong_diep.startswith("E ") for c in cac_ca) ✓ "AssertionError" in {c.loai_loi for c in cac_ca}
A13: 12 | B13: Unit | C13: test_ai_report.py | D13: TestDocKetQua | E13: test_traceback_da_duoc_loc | F13: 1 | G13: 【Ý NGHĨA】 Đây là điểm mấu chốt: traceback tuyệt đối không được mang mật khẩu. 【DỮ LIỆU CHUẨN BỊ】 • bao_cao_mau: — 【CÁC BƯỚC THỰC THI】 1. cac_ca = collect.trich_ca_loi(collect.doc_bao_cao(bao_cao_mau)) 2. toan_bo = " ".join(c.traceback for c in cac_ca) 【KẾT QUẢ MONG ĐỢI】 ✓ "SieuBiMat99" not in toan_bo ✓ redact.NHAN_CHE in toan_bo
... A265: 264 | B265: E2E | C265: test_customer_flow.py | D265: TestDanhGiaSanPham | E265: test_khach_chua_dang_nhap_khong_viet_duoc_danh_gia | F265: 1 | G265: 【Ý NGHĨA】 Khach chua dang nhap khong viet duoc danh gia. 【DỮ LIỆU CHUẨN BỊ】 • page: tab trình duyệt Chromium • site_url: địa chỉ web server test • shop_data: cửa hàng mẫu E2E (3 SP, 3 lô, 1 mã giảm giá) 【CÁC BƯỚC THỰC THI】 1. detail = ProductDetailPage(page, site_url, slug=shop_data["product"].slug).go() 【KẾT QUẢ MONG ĐỢI】 ✓ detail.expect_text_visible("để viết đánh giá")

Sheet Tong hop
A1: BẢNG TỔNG HỢP KIỂM THỬ
A3: Tầng kiểm thử | B3: Số hàm test | C3: Số ca chạy | D3: Tỉ lệ
A4: Unit | B4: =COUNTIF('Danh muc Test Case'!$B$2:$B$265,A4) | C4: =SUMIF('Danh muc Test Case'!$B$2:$B$265,A4,'Danh muc Test Case'!$F$2:$F$265) | D4: =C4/$C$7
A5: Integration | B5: =COUNTIF('Danh muc Test Case'!$B$2:$B$265,A5) | C5: =SUMIF('Danh muc Test Case'!$B$2:$B$265,A5,'Danh muc Test Case'!$F$2:$F$265) | D5: =C5/$C$7
A6: E2E | B6: =COUNTIF('Danh muc Test Case'!$B$2:$B$265,A6) | C6: =SUMIF('Danh muc Test Case'!$B$2:$B$265,A6,'Danh muc Test Case'!$F$2:$F$265) | D6: =C6/$C$7
A7: TỔNG CỘNG | B7: =SUM(B4:B6) | C7: =SUM(C4:C6) | D7: =C7/C7
A9: Thống kê theo tệp
A10: Tệp test | B10: Số hàm test | C10: Số ca chạy
A11: test_admin_flow.py | B11: =COUNTIF('Danh muc Test Case'!$C$2:$C$265,A11) | C11: =SUMIF('Danh muc Test Case'!$C$2:$C$265,A11,'Danh muc Test Case'!$F$2:$F$265)
A12: test_ai_report.py | B12: =COUNTIF('Danh muc Test Case'!$C$2:$C$265,A12) | C12: =SUMIF('Danh muc Test Case'!$C$2:$C$265,A12,'Danh muc Test Case'!$F$2:$F$265)
A13: test_auth_views.py | B13: =COUNTIF('Danh muc Test Case'!$C$2:$C$265,A13) | C13: =SUMIF('Danh muc Test Case'!$C$2:$C$265,A13,'Danh muc Test Case'!$F$2:$F$265)
A14: test_cart_views.py | B14: =COUNTIF('Danh muc Test Case'!$C$2:$C$265,A14) | C14: =SUMIF('Danh muc Test Case'!$C$2:$C$265,A14,'Danh muc Test Case'!$F$2:$F$265)
A15: test_catalog_views.py | B15: =COUNTIF('Danh muc Test Case'!$C$2:$C$265,A15) | C15: =SUMIF('Danh muc Test Case'!$C$2:$C$265,A15,'Danh muc Test Case'!$F$2:$F$265)
A16: test_customer_flow.py | B16: =COUNTIF('Danh muc Test Case'!$C$2:$C$265,A16) | C16: =SUMIF('Danh muc Test Case'!$C$2:$C$265,A16,'Danh muc Test Case'!$F$2:$F$265)
A17: test_dashboard.py | B17: =COUNTIF('Danh muc Test Case'!$C$2:$C$265,A17) | C17: =SUMIF('Danh muc Test Case'!$C$2:$C$265,A17,'Danh muc Test Case'!$F$2:$F$265)
A18: test_models.py | B18: =COUNTIF('Danh muc Test Case'!$C$2:$C$265,A18) | C18: =SUMIF('Danh muc Test Case'!$C$2:$C$265,A18,'Danh muc Test Case'!$F$2:$F$265)
A19: test_permissions.py | B19: =COUNTIF('Danh muc Test Case'!$C$2:$C$265,A19) | C19: =SUMIF('Danh muc Test Case'!$C$2:$C$265,A19,'Danh muc Test Case'!$F$2:$F$265)
A20: test_services.py | B20: =COUNTIF('Danh muc Test Case'!$C$2:$C$265,A20) | C20: =SUMIF('Danh muc Test Case'!$C$2:$C$265,A20,'Danh muc Test Case'!$F$2:$F$265)
A21: test_templates.py | B21: =COUNTIF('Danh muc Test Case'!$C$2:$C$265,A21) | C21: =SUMIF('Danh muc Test Case'!$C$2:$C$265,A21,'Danh muc Test Case'!$F$2:$F$265)

Sheet Chu giai Fixture
A1: DỮ LIỆU MẪU (FIXTURE) DÙNG TRONG TEST
A3: Tên fixture | B3: Ý nghĩa
A4: db | B4: kết nối database sạch
A5: transactional_db | B5: database ghi thật (cho E2E)
A6: client | B6: Django test client (giả lập trình duyệt qua HTTP)
A7: page | B7: tab trình duyệt Chromium
A8: site_url | B8: địa chỉ web server test
A9: settings | B9: ghi đè cấu hình Django
A10: tmp_path | B10: thư mục tạm
A11: customer | B11: khách hàng có sẵn (khachhang)
A12: other_customer | B12: khách hàng thứ hai
A13: staff_user | B13: admin thường (is_staff, đủ permission Django)
A14: superuser | B14: superuser toàn quyền
... A46: url | B46: đường dẫn đang xét (chạy lặp)
